jupyterhub_idle_culler/__init__.py
jupyterhub_idle_culler/__main__.py
jupyterhub_idle_culler-1.4.0.dist-info/METADATA
jupyterhub_idle_culler-1.4.0.dist-info/WHEEL
jupyterhub_idle_culler-1.4.0.dist-info/entry_points.txt
jupyterhub_idle_culler-1.4.0.dist-info/licenses/COPYING.md
jupyterhub_idle_culler-1.4.0.dist-info/RECORD
