Metadata-Version: 2.3
Name: jupyterhub-idle-culler
Version: 1.4.0
Summary: JupyterHub Python repository template
Project-URL: Documentation, https://github.com/jupyterhub/jupyterhub-idle-culler#readme
Project-URL: Source, https://github.com/jupyterhub/jupyterhub-idle-culler
Project-URL: Issues, https://github.com/jupyterhub/jupyterhub-idle-culler/issues
Author-email: Jupyter Contributors <jupyter@googlegroups.com>
License: # The Jupyter multi-user notebook server licensing terms
License-File: COPYING.md
Keywords: jupyterhub
Classifier: Development Status :: 5 - Production/Stable
Classifier: Programming Language :: Python :: 3
Requires-Python: >=3.7
Requires-Dist: packaging
Requires-Dist: python-dateutil
Requires-Dist: tornado
Provides-Extra: test
Requires-Dist: jupyterhub; extra == 'test'
Requires-Dist: jupyterlab; extra == 'test'
Requires-Dist: notebook; extra == 'test'
Requires-Dist: nullauthenticator; extra == 'test'
Requires-Dist: psutil; extra == 'test'
Requires-Dist: pytest; extra == 'test'
Requires-Dist: pytest-asyncio; extra == 'test'
Requires-Dist: pytest-cov; extra == 'test'
